{
  "last_global_step": 0,
  "in_channels": 1,
  "out_channels": 1,
  "in_channels_emb": 0,
  "dropout": 0.0,
  "sigma_max": 16,
  "sigma_min": 4e-05,
  "sigma_data": 1.0,
  "in_num_freqs": 256,
  "in_psd_freqs": 3328,
  "mel_density_scale": 0.54,
  "audio_sample_rate": 32000,
  "model_channels": 32,
  "logvar_channels": 192,
  "channel_mult": [
    1,
    2,
    3,
    4
  ],
  "double_midblock": true,
  "midblock_attn": false,
  "channel_mult_noise": 4,
  "channel_mult_emb": 4,
  "channels_per_head": 16,
  "num_layers_per_block": 2,
  "label_balance": 0.5,
  "concat_balance": 0.5,
  "res_balance": 0.3,
  "attn_balance": 0.3,
  "attn_levels": [],
  "mlp_multiplier": 2,
  "mlp_groups": 1,
  "emb_linear_groups": 1,
  "add_constant_channel": true
}